[
    {
        "name": "Abigail"
    },
    {
        "name": "Alektusv7"
    },
    {
        "name": "Arcan"
    },
    {
        "name": "Arrax"
    },
    {
        "name": "Axel"
    },
    {
        "name": "Che"
    },
    {
        "name": "Clara"
    },
    {
        "name": "Denchor"
    },
    {
        "name": "Elías"
    },
    {
        "name": "Gabri"
    },
    {
        "name": "Hache"
    },   
    {
        "name": "Ignasi"
    },
    {
        "name": "Itachi"
    },
    {
        "name": "Qtus"
    },
    {
        "name": "Matías"
    },
    {
        "name": "Miguel"
    },
    {
        "name": "Miquel"
    },
    {
        "name": "Ninshello"
    },
    {
        "name": "Rubén"
    },
    {
        "name": "Sarki"
    },
    {
        "name": "Simonet"
    },
    {
        "name": "Toxà"
    },
    {
        "name": "Zatara"
    },
    {
        "name": "Zavierazo"
    }

]
